<?xml version='1.0' encoding='UTF-8' standalone='yes'?>
<tomtom version="5.1.0" release="Fri Oct 11 15:53:28 2019 -0700">
  <model>
    <command_line>tomtom -o layer3/tomtom_38.sel.ppm.meme layer3/kernel-38.sel.ppm.meme JASPAR2020.txt</command_line>
    <distance_measure value="ed"/>
    <threshold type="qvalue">0.5</threshold>
    <alphabet name="DNA" like="dna">
      <letter id="A" symbol="A" complement="T" name="Adenine" colour="CC0000"/>
      <letter id="C" symbol="C" complement="G" name="Cytosine" colour="0000CC"/>
      <letter id="G" symbol="G" complement="C" name="Guanine" colour="FFB300"/>
      <letter id="T" symbol="T" aliases="U" complement="A" name="Thymine" colour="008000"/>
      <letter id="N" symbol="N" aliases="X." equals="ACGT" name="Any base"/>
      <letter id="V" symbol="V" equals="ACG" name="Not T"/>
      <letter id="H" symbol="H" equals="ACT" name="Not G"/>
      <letter id="D" symbol="D" equals="AGT" name="Not C"/>
      <letter id="B" symbol="B" equals="CGT" name="Not A"/>
      <letter id="M" symbol="M" equals="AC" name="Amino"/>
      <letter id="R" symbol="R" equals="AG" name="Purine"/>
      <letter id="W" symbol="W" equals="AT" name="Weak"/>
      <letter id="S" symbol="S" equals="CG" name="Strong"/>
      <letter id="Y" symbol="Y" equals="CT" name="Pyrimidine"/>
      <letter id="K" symbol="K" equals="GT" name="Keto"/>
    </alphabet>
    <strands>both</strands>
    <background from="--query--" A="0.25" C="0.25" G="0.25" T="0.25"/>
    <host>g05</host>
    <when>Wed Aug 18 22:04:46 2021</when>
  </model>
  <query_dbs>
    <db source="layer3/kernel-38.sel.ppm.meme" name="kernel-38.sel.ppm" loaded="9" excluded="0" last_mod_date="Wed Aug 18 22:04:46 2021"/>
  </query_dbs>
  <target_dbs>
    <db source="JASPAR2020.txt" name="JASPAR2020.txt" loaded="1011" excluded="0" last_mod_date="Sun Jan 10 05:23:30 2021"/>
  </target_dbs>
  <queries>
    <motif db="0" id="0001_0008_535_0.3058_0.2877_021_119" length="99" nsites="998">
      <pos A="0.603171" C="0.10823" G="0.0481162" T="0.240482"/>
      <pos A="0.284852" C="0.164502" G="0.101319" T="0.449328"/>
      <pos A="0.156322" C="0.0441086" G="0.123259" T="0.67631"/>
      <pos A="0.24449" C="0.0180592" G="0.0451105" T="0.692341"/>
      <pos A="0.178364" C="0.0471143" G="0.0370953" T="0.737426"/>
      <pos A="0.0841846" C="0.127267" G="0.0581352" T="0.730413"/>
      <pos A="0.0752435" C="0.0210859" G="0.766247" T="0.137423"/>
      <pos A="0.0711599" C="0.0541276" G="0.856652" T="0.0180592"/>
      <pos A="0.877693" C="0.0431067" G="0.0421048" T="0.0370953"/>
      <pos A="0.958847" C="2.50476e-05" G="0.0160554" T="0.0250725"/>
      <pos A="0.871553" C="2.50476e-05" G="0.0511729" T="0.0772493"/>
      <pos A="0.952883" C="2.50476e-05" G="0.010034" T="0.0370583"/>
      <pos A="0.733152" C="0.0130627" G="0.00203085" T="0.251755"/>
      <pos A="0.00503455" C="0.976881" G="0.00102695" T="0.0170573"/>
      <pos A="0.00303075" C="0.00603645" G="0.952836" T="0.0380972"/>
      <pos A="0.0390601" C="2.50476e-05" G="2.50476e-05" T="0.96089"/>
      <pos A="0.00904214" C="2.50476e-05" G="0.989906" T="0.00102695"/>
      <pos A="0.995921" C="2.50476e-05" G="2.50476e-05" T="0.00402865"/>
      <pos A="0.996919" C="0.00202885" G="0.00102695" T="2.50476e-05"/>
      <pos A="2.50476e-05" C="2.50476e-05" G="0.00402865" T="0.995921"/>
      <pos A="0.997923" C="2.50476e-05" G="2.50476e-05" T="0.00202685"/>
      <pos A="2.50476e-05" C="2.50476e-05" G="0.999925" T="2.50476e-05"/>
      <pos A="0.00202685" C="2.50476e-05" G="0.997923" T="2.50476e-05"/>
      <pos A="0.00202685" C="2.50476e-05" G="2.50476e-05" T="0.997923"/>
      <pos A="0.999925" C="2.50476e-05" G="2.50476e-05" T="2.50476e-05"/>
      <pos A="2.50476e-05" C="2.50476e-05" G="0.999925" T="2.50476e-05"/>
      <pos A="0.999925" C="2.50476e-05" G="2.50476e-05" T="2.50476e-05"/>
      <pos A="2.50476e-05" C="2.50476e-05" G="2.50476e-05" T="0.999925"/>
      <pos A="2.50476e-05" C="2.50476e-05" G="2.50476e-05" T="0.999925"/>
      <pos A="2.50476e-05" C="2.50476e-05" G="0.999925" T="2.50476e-05"/>
      <pos A="2.50476e-05" C="2.50476e-05" G="0.999925" T="2.50476e-05"/>
      <pos A="0.999925" C="2.50476e-05" G="2.50476e-05" T="2.50476e-05"/>
      <pos A="0.985912" C="2.50476e-05" G="0.0140376" T="2.50476e-05"/>
      <pos A="0.985912" C="2.50476e-05" G="0.0140376" T="2.50476e-05"/>
      <pos A="0.999925" C="2.50476e-05" G="2.50476e-05" T="2.50476e-05"/>
      <pos A="0.999925" C="2.50476e-05" G="2.50476e-05" T="2.50476e-05"/>
      <pos A="0.0140376" C="2.50476e-05" G="2.50476e-05" T="0.985912"/>
      <pos A="0.0140376" C="2.50476e-05" G="2.50476e-05" T="0.985912"/>
      <pos A="0.0140376" C="2.50476e-05" G="0.985912" T="2.50476e-05"/>
      <pos A="2.50476e-05" C="2.50476e-05" G="0.999925" T="2.50476e-05"/>
      <pos A="0.0160394" C="2.50476e-05" G="2.50476e-05" T="0.98391"/>
      <pos A="0.984911" C="2.50476e-05" G="2.50476e-05" T="0.0150385"/>
      <pos A="0.00403265" C="2.50476e-05" G="0.00403265" T="0.99191"/>
      <pos A="2.50476e-05" C="2.50476e-05" G="0.999925" T="2.50476e-05"/>
      <pos A="0.98391" C="2.50476e-05" G="2.50476e-05" T="0.0160394"/>
      <pos A="2.50476e-05" C="0.999925" G="2.50476e-05" T="2.50476e-05"/>
      <pos A="0.998924" C="2.50476e-05" G="2.50476e-05" T="0.00102595"/>
      <pos A="0.987914" C="0.0120358" G="2.50476e-05" T="2.50476e-05"/>
      <pos A="0.0140376" C="2.50476e-05" G="2.50476e-05" T="0.985912"/>
      <pos A="0.998924" C="2.50476e-05" G="2.50476e-05" T="0.00102595"/>
      <pos A="0.00703834" C="0.010044" G="0.953837" T="0.0290801"/>
      <pos A="0.0120478" C="0.9869" G="0.00102695" T="2.50476e-05"/>
      <pos A="0.9869" C="0.00102695" G="0.0120478" T="2.50476e-05"/>
      <pos A="0.983894" C="0.0120478" G="0.00403265" T="2.50476e-05"/>
      <pos A="0.0290801" C="0.955841" G="2.50476e-05" T="0.0150535"/>
      <pos A="0.0280782" C="0.00102695" G="0.0170573" T="0.953837"/>
      <pos A="0.958806" C="0.0180772" G="0.0190801" T="0.00403665"/>
      <pos A="0.0130627" C="0.0120598" G="0.9568" T="0.0180772"/>
      <pos A="0.98391" C="0.0150385" G="2.50476e-05" T="0.00102595"/>
      <pos A="0.0451105" C="0.00503455" G="0.0130497" T="0.936805"/>
      <pos A="0.0530727" C="2.50476e-05" G="0.0170403" T="0.929862"/>
      <pos A="0.00603645" C="0.0170573" G="0.943818" T="0.0330877"/>
      <pos A="0.0560754" C="2.50476e-05" G="0.918852" T="0.0250475"/>
      <pos A="0.909754" C="2.50476e-05" G="0.0240706" T="0.0661504"/>
      <pos A="0.0942036" C="0.00804024" G="0.0711599" T="0.826595"/>
      <pos A="0.899735" C="0.0260744" G="0.0741656" T="2.50476e-05"/>
      <pos A="0.0690871" C="2.50476e-05" G="0.874812" T="0.0560754"/>
      <pos A="0.924782" C="0.010044" G="0.00503455" T="0.060139"/>
      <pos A="0.0580772" C="0.00502955" G="0.0540736" T="0.88282"/>
      <pos A="0.92786" C="2.50476e-05" G="0.0550745" T="0.0170403"/>
      <pos A="0.0580772" C="0.00603045" G="0.0320538" T="0.903838"/>
      <pos A="0.0672203" C="0.847483" G="0.010054" T="0.0752435"/>
      <pos A="0.903742" C="0.00102695" G="0.0340896" T="0.0611409"/>
      <pos A="0.0240706" C="0.0330877" G="0.867673" T="0.0751675"/>
      <pos A="0.0691561" C="0.0591371" G="0.0120478" T="0.859658"/>
      <pos A="0.904648" C="0.0180772" G="0.05017" T="0.0271033"/>
      <pos A="0.89172" C="2.50476e-05" G="0.0671523" T="0.0411029"/>
      <pos A="0.0380972" C="0.020063" G="0.0541276" T="0.887712"/>
      <pos A="0.149309" C="0.00202885" G="0.822588" T="0.0260744"/>
      <pos A="0.0992131" C="2.50476e-05" G="0.830603" T="0.070158"/>
      <pos A="0.0771713" C="0.0120478" G="0.826595" T="0.0841846"/>
      <pos A="0.824591" C="2.50476e-05" G="0.106226" T="0.0691561"/>
      <pos A="0.829601" C="0.0240706" G="0.142296" T="0.00403265"/>
      <pos A="0.848637" C="0.0140516" G="0.0962074" T="0.0411029"/>
      <pos A="0.126391" C="0.807366" G="0.0571913" T="0.00905114"/>
      <pos A="0.169177" C="0.789736" G="0.0170403" T="0.0240466"/>
      <pos A="0.92879" C="0.0330877" G="0.0290801" T="0.00904214"/>
      <pos A="0.852645" C="0.115244" G="0.00603645" T="0.0260744"/>
      <pos A="0.0720898" C="0.112126" G="2.50476e-05" T="0.815759"/>
      <pos A="0.148158" C="0.803749" G="0.0270493" T="0.0210439"/>
      <pos A="0.136284" C="0.0150535" G="0.0771713" T="0.771491"/>
      <pos A="0.805555" C="0.0431067" G="0.0441086" T="0.107228"/>
      <pos A="0.806557" C="0.0992131" G="0.0390991" T="0.0551295"/>
      <pos A="0.107228" C="0.724401" G="0.0320858" T="0.136284"/>
      <pos A="0.330653" C="0.509994" G="0.0721618" T="0.0871903"/>
      <pos A="0.647255" C="0.070158" G="0.0330877" T="0.249499"/>
      <pos A="0.69735" C="0.212429" G="0.0120478" T="0.0781732"/>
      <pos A="0.169347" C="0.219442" G="0.0120478" T="0.599163"/>
      <pos A="0.227229" C="0.629592" G="0.110124" T="0.0330547"/>
    </motif>
    <motif db="0" id="0001_0009_626_0.3152_0.2850_020_125" length="106" nsites="999">
      <pos A="0.633596" C="0.0490691" G="0.0340556" T="0.28328"/>
      <pos A="0.659278" C="0.204414" G="0.0120478" T="0.124261"/>
      <pos A="0.106226" C="0.175358" G="0.0511219" T="0.667293"/>
      <pos A="0.235472" C="0.0140516" G="0.0210649" T="0.729411"/>
      <pos A="0.252505" C="0.00904212" G="0.0190611" T="0.719392"/>
      <pos A="0.150311" C="0.020063" G="0.0380972" T="0.791529"/>
      <pos A="0.0942036" C="0.0380972" G="0.05012" T="0.817578"/>
      <pos A="0.0881042" C="0.00703132" G="0.61658" T="0.288284"/>
      <pos A="0.123136" C="0.0210439" G="0.622586" T="0.233235"/>
      <pos A="0.709373" C="0.0250725" G="0.0471143" T="0.21844"/>
      <pos A="0.758466" C="0.0160554" G="0.169347" T="0.0561314"/>
      <pos A="0.725403" C="0.0431067" G="0.179366" T="0.0521238"/>
      <pos A="0.862664" C="0.0220668" G="0.0541276" T="0.0611409"/>
      <pos A="0.591148" C="0.030082" G="0.0230687" T="0.3557"/>
      <pos A="0.171351" C="0.657274" G="0.0952055" T="0.0761694"/>
      <pos A="0.183374" C="0.0160554" G="0.643248" T="0.157324"/>
      <pos A="0.240482" C="0.0110459" G="0.060139" T="0.688333"/>
      <pos A="0.104223" C="0.106226" G="0.7234" T="0.0661504"/>
      <pos A="0.788523" C="0.00403262" G="0.16033" T="0.0471143"/>
      <pos A="0.82943" C="0.0140656" G="0.0321178" T="0.124386"/>
      <pos A="0.142296" C="0.00102692" G="0.117247" T="0.73943"/>
      <pos A="0.871681" C="0.0250725" G="0.0831827" T="0.020063"/>
      <pos A="0.151313" C="0.00603642" G="0.814572" T="0.0280782"/>
      <pos A="0.0610799" C="2.50225e-05" G="0.783731" T="0.155164"/>
      <pos A="0.115243" C="0.0290801" G="0.0641466" T="0.791529"/>
      <pos A="0.819582" C="0.010044" G="0.150311" T="0.020063"/>
      <pos A="0.0580772" C="0.010034" G="0.889826" T="0.0420628"/>
      <pos A="0.876691" C="0.00804022" G="0.0220668" T="0.0932017"/>
      <pos A="0.0710889" C="2.50225e-05" G="0.0250475" T="0.903839"/>
      <pos A="0.020043" C="2.50225e-05" G="0.0991141" T="0.880818"/>
      <pos A="0.0630817" C="2.50225e-05" G="0.904839" T="0.0320538"/>
      <pos A="0.0770943" C="2.50225e-05" G="0.875813" T="0.0470673"/>
      <pos A="0.928861" C="2.50225e-05" G="0.0320538" T="0.0390601"/>
      <pos A="0.954884" C="2.50225e-05" G="0.030052" T="0.0150385"/>
      <pos A="0.989916" C="2.50225e-05" G="0.010034" T="2.50225e-05"/>
      <pos A="0.9719" C="2.50225e-05" G="0.0150385" T="0.0130367"/>
      <pos A="0.956886" C="2.50225e-05" G="2.50225e-05" T="0.0430637"/>
      <pos A="0.0340896" C="2.50225e-05" G="0.0130497" T="0.952836"/>
      <pos A="0.0210649" C="0.00804022" G="0.0380972" T="0.932798"/>
      <pos A="2.50225e-05" C="2.50225e-05" G="0.970899" T="0.0290511"/>
      <pos A="0.0130497" C="2.50225e-05" G="0.956843" T="0.030082"/>
      <pos A="0.0610799" C="2.50225e-05" G="0.0130367" T="0.925858"/>
      <pos A="0.911846" C="2.50225e-05" G="0.0170403" T="0.0710889"/>
      <pos A="0.0230687" C="2.50225e-05" G="0.0240706" T="0.952836"/>
      <pos A="0.0190801" C="0.0130627" G="0.958806" T="0.00905112"/>
      <pos A="0.940813" C="0.00703832" G="0.00904212" T="0.0431067"/>
      <pos A="0.030082" C="0.962855" G="0.00703832" T="2.50225e-05"/>
      <pos A="0.977883" C="0.00904212" G="2.50225e-05" T="0.0130497"/>
      <pos A="0.985912" C="0.00703132" G="2.50225e-05" T="0.00703132"/>
      <pos A="0.0230687" C="2.50225e-05" G="0.00804022" T="0.968866"/>
      <pos A="0.979887" C="0.00804022" G="0.00703832" T="0.00503452"/>
      <pos A="0.0180772" C="0.0431497" G="0.933733" T="0.00503952"/>
      <pos A="0.0160394" C="0.978906" G="0.00502952" T="2.50225e-05"/>
      <pos A="0.991918" C="0.00803222" G="2.50225e-05" T="2.50225e-05"/>
      <pos A="0.988915" C="0.00703132" G="2.50225e-05" T="0.00402862"/>
      <pos A="2.50225e-05" C="0.992919" G="2.50225e-05" T="0.00703132"/>
      <pos A="0.00703132" C="2.50225e-05" G="2.50225e-05" T="0.992919"/>
      <pos A="0.992919" C="2.50225e-05" G="0.00703132" T="2.50225e-05"/>
      <pos A="0.00703132" C="2.50225e-05" G="0.992919" T="2.50225e-05"/>
      <pos A="0.992919" C="2.50225e-05" G="2.50225e-05" T="0.00703132"/>
      <pos A="2.50225e-05" C="2.50225e-05" G="2.50225e-05" T="0.999925"/>
      <pos A="2.50225e-05" C="2.50225e-05" G="2.50225e-05" T="0.999925"/>
      <pos A="2.50225e-05" C="2.50225e-05" G="0.999925" T="2.50225e-05"/>
      <pos A="2.50225e-05" C="2.50225e-05" G="0.999925" T="2.50225e-05"/>
      <pos A="0.999925" C="2.50225e-05" G="2.50225e-05" T="2.50225e-05"/>
      <pos A="0.10612" C="2.50225e-05" G="2.50225e-05" T="0.89383"/>
      <pos A="0.981909" C="2.50225e-05" G="0.0180412" T="2.50225e-05"/>
      <pos A="2.50225e-05" C="2.50225e-05" G="0.999925" T="2.50225e-05"/>
      <pos A="0.999925" C="2.50225e-05" G="2.50225e-05" T="2.50225e-05"/>
      <pos A="2.50225e-05" C="2.50225e-05" G="2.50225e-05" T="0.999925"/>
      <pos A="0.999925" C="2.50225e-05" G="2.50225e-05" T="2.50225e-05"/>
      <pos A="2.50225e-05" C="2.50225e-05" G="2.50225e-05" T="0.999925"/>
      <pos A="2.50225e-05" C="0.999925" G="2.50225e-05" T="2.50225e-05"/>
      <pos A="0.999925" C="2.50225e-05" G="2.50225e-05" T="2.50225e-05"/>
      <pos A="2.50225e-05" C="2.50225e-05" G="0.999925" T="2.50225e-05"/>
      <pos A="2.50225e-05" C="2.50225e-05" G="2.50225e-05" T="0.999925"/>
      <pos A="0.995921" C="2.50225e-05" G="0.00402862" T="2.50225e-05"/>
      <pos A="0.999925" C="2.50225e-05" G="2.50225e-05" T="2.50225e-05"/>
      <pos A="2.50225e-05" C="2.50225e-05" G="2.50225e-05" T="0.999925"/>
      <pos A="2.50225e-05" C="2.50225e-05" G="0.999925" T="2.50225e-05"/>
      <pos A="2.50225e-05" C="2.50225e-05" G="0.999925" T="2.50225e-05"/>
      <pos A="2.50225e-05" C="2.50225e-05" G="0.999925" T="2.50225e-05"/>
      <pos A="0.997923" C="2.50225e-05" G="2.50225e-05" T="0.00202682"/>
      <pos A="0.990917" C="2.50225e-05" G="0.00903312" T="2.50225e-05"/>
      <pos A="0.984911" C="2.50225e-05" G="2.50225e-05" T="0.0150385"/>
      <pos A="0.00903312" C="0.990917" G="2.50225e-05" T="2.50225e-05"/>
      <pos A="0.0110459" C="0.983895" G="2.50225e-05" T="0.00503452"/>
      <pos A="0.985898" C="2.50225e-05" G="0.00202882" T="0.0120478"/>
      <pos A="0.977883" C="2.50225e-05" G="0.0140516" T="0.00804022"/>
      <pos A="0.0130627" C="0.00503952" G="0.0140656" T="0.967832"/>
      <pos A="0.0190421" C="0.954884" G="0.0150385" T="0.0110349"/>
      <pos A="0.0561314" C="0.00904212" G="0.0721618" T="0.862664"/>
      <pos A="0.936805" C="0.010044" G="0.020063" T="0.0330877"/>
      <pos A="0.914763" C="0.0320858" G="0.0290801" T="0.0240706"/>
      <pos A="0.0230687" C="0.908752" G="0.0270763" T="0.0411029"/>
      <pos A="0.258516" C="0.602169" G="0.0932017" T="0.0461124"/>
      <pos A="0.670629" C="0.00903312" G="0.0830997" T="0.237238"/>
      <pos A="0.868675" C="0.0681542" G="0.00703832" T="0.0561314"/>
      <pos A="0.0330877" C="0.121255" G="0.030082" T="0.815574"/>
      <pos A="0.103118" C="0.810755" G="0.0520718" T="0.0340556"/>
      <pos A="0.150311" C="0.0421048" G="0.304604" T="0.502981"/>
      <pos A="0.827597" C="0.05012" G="0.0240706" T="0.0982112"/>
      <pos A="0.798542" C="0.138288" G="0.0260744" T="0.0370953"/>
      <pos A="0.122135" C="0.755705" G="0.0510709" T="0.0710889"/>
      <pos A="0.623587" C="0.0921078" G="0.0841006" T="0.200205"/>
      <pos A="0.186566" C="0.186566" G="0.209633" T="0.417235"/>
    </motif>
    <motif db="0" id="0001_0011_712_0.3097_0.2921_005_119" length="115" nsites="999">
      <pos A="0.358063" C="0.115359" G="0.358063" T="0.168514"/>
      <pos A="0.070158" C="0.252505" G="0.480939" T="0.196398"/>
      <pos A="0.588555" C="0.0931087" G="0.266264" T="0.0520718"/>
      <pos A="0.768717" C="0.0260484" G="0.0360574" T="0.169177"/>
      <pos A="0.620826" C="0.231697" G="0.0180772" T="0.1294"/>
      <pos A="0.0762464" C="0.0110569" G="0.76725" T="0.145446"/>
      <pos A="0.00202882" C="0.040101" G="0.00603642" T="0.951834"/>
      <pos A="0.887824" C="0.107121" G="0.00102592" T="0.00402862"/>
      <pos A="0.768485" C="0.070158" G="0.00403262" T="0.157324"/>
      <pos A="0.945822" C="0.00703832" G="0.00403262" T="0.0431067"/>
      <pos A="0.9719" C="0.00402862" G="0.00402862" T="0.020043"/>
      <pos A="2.50225e-05" C="2.50225e-05" G="0.00202682" T="0.997923"/>
      <pos A="2.50225e-05" C="0.254509" G="2.50225e-05" T="0.745441"/>
      <pos A="2.50225e-05" C="0.955885" G="0.00102592" T="0.0430637"/>
      <pos A="2.50225e-05" C="0.955885" G="2.50225e-05" T="0.0440646"/>
      <pos A="0.877693" C="2.50225e-05" G="0.10823" T="0.0140516"/>
      <pos A="0.997923" C="2.50225e-05" G="2.50225e-05" T="0.00202682"/>
      <pos A="0.0250725" C="0.00102692" G="0.00603642" T="0.967864"/>
      <pos A="0.00303072" C="0.0761694" G="0.00102692" T="0.919773"/>
      <pos A="0.0110349" C="2.50225e-05" G="0.00102592" T="0.987914"/>
      <pos A="0.0830997" C="2.50225e-05" G="0.0760934" T="0.840782"/>
      <pos A="2.50225e-05" C="0.0511219" G="2.50225e-05" T="0.948828"/>
      <pos A="0.00102592" C="2.50225e-05" G="0.998924" T="2.50225e-05"/>
      <pos A="2.50225e-05" C="2.50225e-05" G="0.999925" T="2.50225e-05"/>
      <pos A="0.999925" C="2.50225e-05" G="2.50225e-05" T="2.50225e-05"/>
      <pos A="0.999925" C="2.50225e-05" G="2.50225e-05" T="2.50225e-05"/>
      <pos A="0.99492" C="2.50225e-05" G="0.00302772" T="0.00202682"/>
      <pos A="0.999925" C="2.50225e-05" G="2.50225e-05" T="2.50225e-05"/>
      <pos A="0.651612" C="2.50225e-05" G="2.50225e-05" T="0.348338"/>
      <pos A="2.50225e-05" C="0.999925" G="2.50225e-05" T="2.50225e-05"/>
      <pos A="2.50225e-05" C="2.50225e-05" G="0.937869" T="0.0620808"/>
      <pos A="2.50225e-05" C="2.50225e-05" G="2.50225e-05" T="0.999925"/>
      <pos A="2.50225e-05" C="2.50225e-05" G="0.999925" T="2.50225e-05"/>
      <pos A="0.999925" C="2.50225e-05" G="2.50225e-05" T="2.50225e-05"/>
      <pos A="0.999925" C="2.50225e-05" G="2.50225e-05" T="2.50225e-05"/>
      <pos A="2.50225e-05" C="2.50225e-05" G="2.50225e-05" T="0.999925"/>
      <pos A="0.999925" C="2.50225e-05" G="2.50225e-05" T="2.50225e-05"/>
      <pos A="2.50225e-05" C="2.50225e-05" G="0.999925" T="2.50225e-05"/>
      <pos A="2.50225e-05" C="2.50225e-05" G="0.999925" T="2.50225e-05"/>
      <pos A="2.50225e-05" C="2.50225e-05" G="2.50225e-05" T="0.999925"/>
      <pos A="0.999925" C="2.50225e-05" G="2.50225e-05" T="2.50225e-05"/>
      <pos A="2.50225e-05" C="2.50225e-05" G="0.999925" T="2.50225e-05"/>
      <pos A="0.999925" C="2.50225e-05" G="2.50225e-05" T="2.50225e-05"/>
      <pos A="2.50225e-05" C="2.50225e-05" G="2.50225e-05" T="0.999925"/>
      <pos A="2.50225e-05" C="2.50225e-05" G="2.50225e-05" T="0.999925"/>
      <pos A="2.50225e-05" C="2.50225e-05" G="0.999925" T="2.50225e-05"/>
      <pos A="2.50225e-05" C="2.50225e-05" G="0.999925" T="2.50225e-05"/>
      <pos A="0.999925" C="2.50225e-05" G="2.50225e-05" T="2.50225e-05"/>
      <pos A="0.999925" C="2.50225e-05" G="2.50225e-05" T="2.50225e-05"/>
      <pos A="0.999925" C="2.50225e-05" G="2.50225e-05" T="2.50225e-05"/>
      <pos A="0.999925" C="2.50225e-05" G="2.50225e-05" T="2.50225e-05"/>
      <pos A="0.999925" C="2.50225e-05" G="2.50225e-05" T="2.50225e-05"/>
      <pos A="2.50225e-05" C="2.50225e-05" G="2.50225e-05" T="0.999925"/>
      <pos A="2.50225e-05" C="2.50225e-05" G="2.50225e-05" T="0.999925"/>
      <pos A="2.50225e-05" C="2.50225e-05" G="0.999925" T="2.50225e-05"/>
      <pos A="2.50225e-05" C="2.50225e-05" G="0.999925" T="2.50225e-05"/>
      <pos A="0.00202682" C="2.50225e-05" G="2.50225e-05" T="0.997923"/>
      <pos A="0.997923" C="2.50225e-05" G="2.50225e-05" T="0.00202682"/>
      <pos A="2.50225e-05" C="2.50225e-05" G="2.50225e-05" T="0.999925"/>
      <pos A="2.50225e-05" C="2.50225e-05" G="0.999925" T="2.50225e-05"/>
      <pos A="0.99492" C="2.50225e-05" G="2.50225e-05" T="0.00502952"/>
      <pos A="2.50225e-05" C="0.999925" G="2.50225e-05" T="2.50225e-05"/>
      <pos A="0.999925" C="2.50225e-05" G="2.50225e-05" T="2.50225e-05"/>
      <pos A="0.998924" C="2.50225e-05" G="2.50225e-05" T="0.00102592"/>
      <pos A="0.00102592" C="2.50225e-05" G="2.50225e-05" T="0.998924"/>
      <pos A="0.999925" C="2.50225e-05" G="2.50225e-05" T="2.50225e-05"/>
      <pos A="2.50225e-05" C="0.0130497" G="0.983895" T="0.00303072"/>
      <pos A="2.50225e-05" C="0.999925" G="2.50225e-05" T="2.50225e-05"/>
      <pos A="0.999925" C="2.50225e-05" G="2.50225e-05" T="2.50225e-05"/>
      <pos A="0.985912" C="2.50225e-05" G="2.50225e-05" T="0.0140376"/>
      <pos A="2.50225e-05" C="0.985912" G="0.0140376" T="2.50225e-05"/>
      <pos A="0.0140376" C="2.50225e-05" G="2.50225e-05" T="0.985912"/>
      <pos A="0.985912" C="0.0140376" G="2.50225e-05" T="2.50225e-05"/>
      <pos A="0.0140376" C="2.50225e-05" G="0.985912" T="2.50225e-05"/>
      <pos A="0.999925" C="2.50225e-05" G="2.50225e-05" T="2.50225e-05"/>
      <pos A="2.50225e-05" C="2.50225e-05" G="2.50225e-05" T="0.999925"/>
      <pos A="0.0140376" C="2.50225e-05" G="2.50225e-05" T="0.985912"/>
      <pos A="2.50225e-05" C="2.50225e-05" G="0.999925" T="2.50225e-05"/>
      <pos A="2.50225e-05" C="0.0140376" G="0.985912" T="2.50225e-05"/>
      <pos A="0.999925" C="2.50225e-05" G="2.50225e-05" T="2.50225e-05"/>
      <pos A="0.0720898" C="2.50225e-05" G="2.50225e-05" T="0.92786"/>
      <pos A="0.985912" C="0.0140376" G="2.50225e-05" T="2.50225e-05"/>
      <pos A="2.50225e-05" C="2.50225e-05" G="0.985912" T="0.0140376"/>
      <pos A="0.999925" C="2.50225e-05" G="2.50225e-05" T="2.50225e-05"/>
      <pos A="2.50225e-05" C="2.50225e-05" G="0.0140376" T="0.985912"/>
      <pos A="0.999925" C="2.50225e-05" G="2.50225e-05" T="2.50225e-05"/>
      <pos A="2.50225e-05" C="2.50225e-05" G="2.50225e-05" T="0.999925"/>
      <pos A="2.50225e-05" C="0.985912" G="2.50225e-05" T="0.0140376"/>
      <pos A="0.985912" C="2.50225e-05" G="0.0140376" T="2.50225e-05"/>
      <pos A="2.50225e-05" C="2.50225e-05" G="0.999925" T="2.50225e-05"/>
      <pos A="0.0140376" C="2.50225e-05" G="2.50225e-05" T="0.985912"/>
      <pos A="0.985912" C="2.50225e-05" G="2.50225e-05" T="0.0140376"/>
      <pos A="0.999925" C="2.50225e-05" G="2.50225e-05" T="2.50225e-05"/>
      <pos A="2.50225e-05" C="2.50225e-05" G="2.50225e-05" T="0.999925"/>
      <pos A="2.50225e-05" C="2.50225e-05" G="0.999925" T="2.50225e-05"/>
      <pos A="2.50225e-05" C="2.50225e-05" G="0.999925" T="2.50225e-05"/>
      <pos A="0.0320538" C="2.50225e-05" G="0.967896" T="2.50225e-05"/>
      <pos A="0.967896" C="2.50225e-05" G="2.50225e-05" T="0.0320538"/>
      <pos A="0.967896" C="0.0320538" G="2.50225e-05" T="2.50225e-05"/>
      <pos A="0.999925" C="2.50225e-05" G="2.50225e-05" T="2.50225e-05"/>
      <pos A="0.0320538" C="0.907842" G="0.0170403" T="0.0430637"/>
      <pos A="2.50225e-05" C="0.925858" G="2.50225e-05" T="0.0740916"/>
      <pos A="0.992919" C="0.00703132" G="2.50225e-05" T="2.50225e-05"/>
      <pos A="0.944875" C="2.50225e-05" G="0.0550745" T="2.50225e-05"/>
      <pos A="0.0961114" C="0.0160394" G="2.50225e-05" T="0.887824"/>
      <pos A="0.112126" C="0.813758" G="0.0230457" T="0.0510709"/>
      <pos A="0.0981132" C="0.0830997" G="0.0991141" T="0.719673"/>
      <pos A="0.795741" C="0.0470673" G="0.0790961" T="0.0780952"/>
      <pos A="0.867541" C="0.0561884" G="0.0682232" T="0.00804822"/>
      <pos A="0.171523" C="0.57068" G="0.141435" T="0.116362"/>
      <pos A="0.330653" C="0.371731" G="0.210425" T="0.0871903"/>
      <pos A="0.537045" C="0.128269" G="0.129271" T="0.205415"/>
      <pos A="0.70236" C="0.184376" G="0.00403262" T="0.109232"/>
      <pos A="0.28156" C="0.248497" G="0.0320858" T="0.437857"/>
      <pos A="0.32364" C="0.514002" G="0.121255" T="0.0411029"/>
    </motif>
    <motif db="0" id="0004_0002_2089_0.3022_0.2802_010_122" length="113" nsites="998">
      <pos A="0.173355" C="0.531034" G="0.222448" T="0.0731637"/>
      <pos A="0.142296" C="0.156322" G="0.152315" T="0.549068"/>
      <pos A="0.500977" C="0.289575" G="0.127267" T="0.0821808"/>
      <pos A="0.0862754" C="0.0411439" G="0.174532" T="0.698049"/>
      <pos A="0.0811789" C="0.151313" G="0.10823" T="0.659278"/>
      <pos A="0.78151" C="0.0411029" G="0.0581352" T="0.119251"/>
      <pos A="0.709373" C="0.0320858" G="0.010044" T="0.248497"/>
      <pos A="0.887712" C="0.0380972" G="0.0340896" T="0.040101"/>
      <pos A="0.114242" C="0.0160554" G="0.829601" T="0.040101"/>
      <pos A="0.0280782" C="0.00303075" G="0.0230687" T="0.945822"/>
      <pos A="0.0250725" C="0.810565" G="0.00603645" T="0.158326"/>
      <pos A="0.010044" C="0.96586" G="0.0130497" T="0.0110459"/>
      <pos A="0.00904214" C="0.973875" G="0.00303075" T="0.0140516"/>
      <pos A="0.936805" C="0.00703834" G="0.0180592" T="0.0380972"/>
      <pos A="0.929792" C="0.0150535" G="0.00804024" T="0.0471143"/>
      <pos A="0.0421468" C="0.00403665" G="0.0230917" T="0.930724"/>
      <pos A="0.0421048" C="0.00403265" G="0.0390991" T="0.914763"/>
      <pos A="0.0320858" C="0.00904214" G="0.152315" T="0.806557"/>
      <pos A="0.777502" C="0.010044" G="0.00503455" T="0.207419"/>
      <pos A="0.0581942" C="0.0712319" G="0.0250975" T="0.845477"/>
      <pos A="0.0260484" C="0.010034" G="0.943874" T="0.020043"/>
      <pos A="0.00803225" C="0.0150385" G="0.973901" T="0.00302775"/>
      <pos A="0.982893" C="0.00603645" G="0.00703834" T="0.00403265"/>
      <pos A="0.982893" C="0.00403265" G="0.00703834" T="0.00603645"/>
      <pos A="0.987902" C="0.00503455" G="2.50476e-05" T="0.00703834"/>
      <pos A="0.973875" C="0.00202885" G="0.010044" T="0.0140516"/>
      <pos A="0.0120358" C="2.50476e-05" G="0.00603045" T="0.981909"/>
      <pos A="0.0110459" C="0.974877" G="0.00503455" T="0.00904214"/>
      <pos A="0.00804824" C="0.00503955" G="0.969838" T="0.0170743"/>
      <pos A="0.0120478" C="2.50476e-05" G="0.00303075" T="0.984896"/>
      <pos A="0.0130367" C="2.50476e-05" G="0.98291" T="0.00402865"/>
      <pos A="0.987914" C="2.50476e-05" G="0.010034" T="0.00202685"/>
      <pos A="0.996919" C="2.50476e-05" G="2.50476e-05" T="0.00303075"/>
      <pos A="0.0130497" C="0.00603645" G="2.50476e-05" T="0.980889"/>
      <pos A="0.986913" C="2.50476e-05" G="2.50476e-05" T="0.0130367"/>
      <pos A="0.971872" C="0.00703834" G="0.00904214" T="0.0120478"/>
      <pos A="0.00804024" C="2.50476e-05" G="0.010044" T="0.981891"/>
      <pos A="0.0130497" C="2.50476e-05" G="2.50476e-05" T="0.9869"/>
      <pos A="0.987902" C="2.50476e-05" G="0.0110459" T="0.00102695"/>
      <pos A="0.0150535" C="0.00603645" G="0.978885" T="2.50476e-05"/>
      <pos A="0.983894" C="0.010044" G="2.50476e-05" T="0.00603645"/>
      <pos A="2.50476e-05" C="0.982893" G="2.50476e-05" T="0.0170573"/>
      <pos A="0.00102595" C="0.010034" G="0.00703135" T="0.981909"/>
      <pos A="0.00703834" C="0.968866" G="0.0140516" T="0.010044"/>
      <pos A="0.0140516" C="0.00303075" G="0.962855" T="0.020063"/>
      <pos A="0.986913" C="2.50476e-05" G="0.00502955" T="0.00803225"/>
      <pos A="0.993913" C="2.50476e-05" G="0.00303075" T="0.00303075"/>
      <pos A="0.985884" C="2.50476e-05" G="0.00102795" T="0.0130627"/>
      <pos A="0.977883" C="0.00503455" G="0.00202885" T="0.0150535"/>
      <pos A="0.978906" C="0.00903314" G="0.00102595" T="0.0110349"/>
      <pos A="0.0140516" C="0.00804024" G="2.50476e-05" T="0.977883"/>
      <pos A="0.0110459" C="0.00102695" G="0.00603645" T="0.981891"/>
      <pos A="0.0110569" C="0.00102795" G="0.979867" T="0.00804824"/>
      <pos A="0.00603645" C="0.0110459" G="0.979887" T="0.00303075"/>
      <pos A="0.94482" C="0.00603645" G="0.0110459" T="0.0380972"/>
      <pos A="0.652919" C="0.00604244" G="0.0291091" T="0.31193"/>
      <pos A="0.631225" C="2.50476e-05" G="0.00303075" T="0.365719"/>
      <pos A="0.0130497" C="0.00503455" G="0.961853" T="0.020063"/>
      <pos A="0.0360574" C="2.50476e-05" G="0.0130367" T="0.950881"/>
      <pos A="0.0220668" C="0.956843" G="0.0160554" T="0.00503455"/>
      <pos A="0.971872" C="0.00303075" G="0.0150535" T="0.010044"/>
      <pos A="0.979887" C="0.00202885" G="0.00703834" T="0.0110459"/>
      <pos A="0.0140656" C="0.00604244" G="0.0120598" T="0.967832"/>
      <pos A="0.603171" C="0.250501" G="0.0170573" T="0.129271"/>
      <pos A="0.0190611" C="0.525022" G="0.435853" T="0.020063"/>
      <pos A="0.0110459" C="0.974877" G="0.00804024" T="0.00603645"/>
      <pos A="0.985912" C="0.00302775" G="0.00703135" T="0.00402865"/>
      <pos A="0.981909" C="0.00502955" G="0.00703135" T="0.00603045"/>
      <pos A="0.0150385" C="0.973901" G="0.00603045" T="0.00502955"/>
      <pos A="0.0110459" C="0.00202885" G="0.00603645" T="0.980889"/>
      <pos A="0.984881" C="0.00905114" G="0.00102795" T="0.00503955"/>
      <pos A="0.0170573" C="0.00202885" G="0.967864" T="0.0130497"/>
      <pos A="0.984911" C="0.00903314" G="0.00302775" T="0.00302775"/>
      <pos A="0.00803225" C="0.00703135" G="0.00703135" T="0.977905"/>
      <pos A="0.0250475" C="2.50476e-05" G="2.50476e-05" T="0.974902"/>
      <pos A="0.00904214" C="0.00202885" G="0.979887" T="0.00904214"/>
      <pos A="0.00804024" C="0.010044" G="0.971872" T="0.010044"/>
      <pos A="0.978885" C="0.00303075" G="0.00904214" T="0.00904214"/>
      <pos A="0.0431067" C="2.50476e-05" G="0.010044" T="0.946824"/>
      <pos A="0.977905" C="0.00803225" G="0.00903314" T="0.00502955"/>
      <pos A="0.00703135" C="0.0160394" G="0.962892" T="0.0140376"/>
      <pos A="0.993913" C="2.50476e-05" G="0.00102695" T="0.00503455"/>
      <pos A="0.00403265" C="0.00102695" G="0.0180592" T="0.976881"/>
      <pos A="0.985898" C="2.50476e-05" G="0.00904214" T="0.00503455"/>
      <pos A="0.010044" C="2.50476e-05" G="0.00503455" T="0.984896"/>
      <pos A="0.0150535" C="0.96586" G="0.00603645" T="0.0130497"/>
      <pos A="0.976858" C="0.00102795" G="0.00804824" T="0.0140656"/>
      <pos A="0.0130367" C="0.0120358" G="0.968897" T="0.00603045"/>
      <pos A="0.0220448" C="0.00803225" G="0.00703135" T="0.962892"/>
      <pos A="0.969898" C="0.00703135" G="0.0150385" T="0.00803225"/>
      <pos A="0.974877" C="0.00603645" G="0.00804024" T="0.0110459"/>
      <pos A="0.0381352" C="2.50476e-05" G="0.00804824" T="0.953791"/>
      <pos A="0.0340896" C="0.0180592" G="0.939811" T="0.00804024"/>
      <pos A="0.0220668" C="0.0150535" G="0.936805" T="0.0260744"/>
      <pos A="0.0331207" C="0.010054" G="0.934735" T="0.0220888"/>
      <pos A="0.926786" C="0.020063" G="0.0230687" T="0.030082"/>
      <pos A="0.933732" C="0.0130627" G="0.0220888" T="0.0311149"/>
      <pos A="0.937807" C="0.0260744" G="0.0190611" T="0.0170573"/>
      <pos A="0.0621428" C="0.894725" G="0.0130497" T="0.030082"/>
      <pos A="0.0972093" C="0.865669" G="0.0190611" T="0.0180592"/>
      <pos A="0.92879" C="0.0330877" G="0.0180592" T="0.020063"/>
      <pos A="0.892614" C="0.0541816" G="0.0160714" T="0.0371323"/>
      <pos A="0.0591371" C="0.0521238" G="0.0390991" T="0.849639"/>
      <pos A="0.080097" C="0.828771" G="0.0330547" T="0.0580772"/>
      <pos A="0.0731637" C="0.0471143" G="0.0861884" T="0.793533"/>
      <pos A="0.866671" C="0.0431067" G="0.0360934" T="0.0541276"/>
      <pos A="0.848637" C="0.0821808" G="0.030082" T="0.0390991"/>
      <pos A="0.131275" C="0.779506" G="0.0230687" T="0.0661504"/>
      <pos A="0.368356" C="0.453433" G="0.0640826" T="0.114128"/>
      <pos A="0.543602" C="0.143441" G="0.0792551" T="0.233703"/>
      <pos A="0.66028" C="0.138288" G="0.0260744" T="0.175358"/>
      <pos A="0.173355" C="0.209423" G="0.0881922" T="0.52903"/>
      <pos A="0.126391" C="0.57068" G="0.190578" T="0.112351"/>
    </motif>
    <motif db="0" id="0004_0003_409_0.3436_0.3222_011_119" length="109" nsites="998">
      <pos A="0.601167" C="0.109232" G="0.0350915" T="0.254509"/>
      <pos A="0.15347" C="0.116362" G="0.628849" T="0.101319"/>
      <pos A="0.171351" C="0.0260744" G="0.129271" T="0.673305"/>
      <pos A="0.0821808" C="0.0160554" G="0.806557" T="0.0952055"/>
      <pos A="0.708371" C="0.0461124" G="0.00703834" T="0.238478"/>
      <pos A="0.899735" C="0.05012" G="0.0130497" T="0.0370953"/>
      <pos A="0.817578" C="0.0551295" G="0.0911979" T="0.0360934"/>
      <pos A="0.792739" C="0.0170403" G="0.0490691" T="0.141152"/>
      <pos A="0.0561884" C="0.00403665" G="0.00905114" T="0.930724"/>
      <pos A="0.0250725" C="0.785517" G="0.00403265" T="0.185377"/>
      <pos A="0.101217" C="0.877693" G="0.00603645" T="0.0150535"/>
      <pos A="0.05017" C="0.896625" G="0.0481642" T="0.00503955"/>
      <pos A="0.13929" C="0.00603645" G="0.792531" T="0.0621428"/>
      <pos A="0.904648" C="0.0130627" G="0.0391381" T="0.0431497"/>
      <pos A="0.0691561" C="0.0160554" G="0.010044" T="0.904744"/>
      <pos A="0.0280502" C="0.0660844" G="0.789736" T="0.116129"/>
      <pos A="0.010044" C="0.690337" G="0.0551295" T="0.24449"/>
      <pos A="0.920775" C="0.00703834" G="2.50476e-05" T="0.0721618"/>
      <pos A="0.73943" C="0.0180592" G="0.00102695" T="0.241484"/>
      <pos A="0.0160554" C="0.00703834" G="0.963856" T="0.0130497"/>
      <pos A="0.0370583" C="0.0130367" G="0.94988" T="2.50476e-05"/>
      <pos A="0.9719" C="0.0130367" G="0.00302775" T="0.0120358"/>
      <pos A="0.970899" C="0.0150385" G="2.50476e-05" T="0.0140376"/>
      <pos A="0.0370953" C="0.00102695" G="0.921777" T="0.040101"/>
      <pos A="0.952789" C="0.010054" G="0.0150685" T="0.0220888"/>
      <pos A="0.221224" C="2.50476e-05" G="0.030052" T="0.748699"/>
      <pos A="0.0130497" C="0.929792" G="0.0521238" T="0.00503455"/>
      <pos A="0.0190611" C="0.0180592" G="0.878695" T="0.0841846"/>
      <pos A="0.904839" C="2.50476e-05" G="0.00603045" T="0.0891051"/>
      <pos A="0.874686" C="2.50476e-05" G="0.114242" T="0.0110459"/>
      <pos A="0.966895" C="2.50476e-05" G="0.0180412" T="0.0150385"/>
      <pos A="0.985912" C="2.50476e-05" G="0.0140376" T="2.50476e-05"/>
      <pos A="0.0260744" C="0.00503455" G="0.0130497" T="0.955841"/>
      <pos A="0.980889" C="2.50476e-05" G="0.0130497" T="0.00603645"/>
      <pos A="0.00502955" C="2.50476e-05" G="0.977905" T="0.0170403"/>
      <pos A="2.50476e-05" C="2.50476e-05" G="0.999925" T="2.50476e-05"/>
      <pos A="0.00102595" C="2.50476e-05" G="0.0190421" T="0.979907"/>
      <pos A="0.993919" C="2.50476e-05" G="0.00102595" T="0.00502955"/>
      <pos A="0.0130367" C="2.50476e-05" G="0.986913" T="2.50476e-05"/>
      <pos A="0.99492" C="2.50476e-05" G="0.00502955" T="2.50476e-05"/>
      <pos A="0.00502955" C="2.50476e-05" G="2.50476e-05" T="0.99492"/>
      <pos A="2.50476e-05" C="2.50476e-05" G="2.50476e-05" T="0.999925"/>
      <pos A="2.50476e-05" C="2.50476e-05" G="0.99492" T="0.00502955"/>
      <pos A="2.50476e-05" C="2.50476e-05" G="0.999925" T="2.50476e-05"/>
      <pos A="0.99492" C="2.50476e-05" G="0.00502955" T="2.50476e-05"/>
      <pos A="0.999925" C="2.50476e-05" G="2.50476e-05" T="2.50476e-05"/>
      <pos A="0.999925" C="2.50476e-05" G="2.50476e-05" T="2.50476e-05"/>
      <pos A="0.999925" C="2.50476e-05" G="2.50476e-05" T="2.50476e-05"/>
      <pos A="0.978906" C="2.50476e-05" G="2.50476e-05" T="0.0210439"/>
      <pos A="0.00502955" C="2.50476e-05" G="2.50476e-05" T="0.99492"/>
      <pos A="2.50476e-05" C="2.50476e-05" G="0.0210439" T="0.978906"/>
      <pos A="2.50476e-05" C="2.50476e-05" G="0.99492" T="0.00502955"/>
      <pos A="0.0220668" C="2.50476e-05" G="0.977883" T="2.50476e-05"/>
      <pos A="0.0250725" C="2.50476e-05" G="0.00503455" T="0.969868"/>
      <pos A="0.99492" C="2.50476e-05" G="2.50476e-05" T="0.00502955"/>
      <pos A="0.00503455" C="2.50476e-05" G="2.50476e-05" T="0.994915"/>
      <pos A="2.50476e-05" C="2.50476e-05" G="0.999925" T="2.50476e-05"/>
      <pos A="0.999925" C="2.50476e-05" G="2.50476e-05" T="2.50476e-05"/>
      <pos A="2.50476e-05" C="0.999925" G="2.50476e-05" T="2.50476e-05"/>
      <pos A="0.999925" C="2.50476e-05" G="2.50476e-05" T="2.50476e-05"/>
      <pos A="0.988915" C="0.0110349" G="2.50476e-05" T="2.50476e-05"/>
      <pos A="2.50476e-05" C="2.50476e-05" G="2.50476e-05" T="0.999925"/>
      <pos A="0.999925" C="2.50476e-05" G="2.50476e-05" T="2.50476e-05"/>
      <pos A="0.0230457" C="2.50476e-05" G="0.976904" T="2.50476e-05"/>
      <pos A="0.0110459" C="0.961853" G="0.0220668" T="0.00503455"/>
      <pos A="0.966862" C="2.50476e-05" G="2.50476e-05" T="0.0330877"/>
      <pos A="0.981891" C="2.50476e-05" G="0.00403265" T="0.0140516"/>
      <pos A="0.00303075" C="0.947826" G="0.0250725" T="0.0240706"/>
      <pos A="0.040101" C="2.50476e-05" G="0.0110459" T="0.948828"/>
      <pos A="0.985912" C="0.0140376" G="2.50476e-05" T="2.50476e-05"/>
      <pos A="0.0240946" C="0.00102795" G="0.96382" T="0.0110569"/>
      <pos A="0.979907" C="2.50476e-05" G="2.50476e-05" T="0.020043"/>
      <pos A="0.00403265" C="0.00403265" G="0.0140516" T="0.977883"/>
      <pos A="0.0180592" C="0.00703834" G="0.020063" T="0.954839"/>
      <pos A="0.0140516" C="2.50476e-05" G="0.961853" T="0.0240706"/>
      <pos A="0.0491181" C="0.00804024" G="0.92879" T="0.0140516"/>
      <pos A="0.916767" C="0.00703834" G="0.0531257" T="0.0230687"/>
      <pos A="0.0981132" C="0.00402865" G="0.0280502" T="0.869808"/>
      <pos A="0.935803" C="0.00303075" G="0.0230687" T="0.0380972"/>
      <pos A="0.0320858" C="2.50476e-05" G="0.904744" T="0.0631447"/>
      <pos A="0.932798" C="0.00202885" G="0.0390991" T="0.0260744"/>
      <pos A="0.0310839" C="0.00303075" G="0.0581352" T="0.90775"/>
      <pos A="0.954839" C="2.50476e-05" G="0.00503455" T="0.040101"/>
      <pos A="0.0150535" C="0.0180592" G="0.0190611" T="0.947826"/>
      <pos A="0.0770943" C="0.886823" G="0.0240466" T="0.0120358"/>
      <pos A="0.913761" C="2.50476e-05" G="0.0561314" T="0.030082"/>
      <pos A="0.0320858" C="0.0290801" G="0.898733" T="0.040101"/>
      <pos A="0.0741656" C="0.00102695" G="0.00804024" T="0.916767"/>
      <pos A="0.936868" C="0.00202685" G="0.0510709" T="0.010034"/>
      <pos A="0.918771" C="0.00503455" G="0.00703834" T="0.0691561"/>
      <pos A="0.0461584" C="0.0271033" G="0.0250975" T="0.90164"/>
      <pos A="0.0811789" C="0.0130497" G="0.885708" T="0.020063"/>
      <pos A="0.0160554" C="0.0230687" G="0.905746" T="0.0551295"/>
      <pos A="0.0591971" C="0.0180772" G="0.889605" T="0.0331207"/>
      <pos A="0.913761" C="0.0150535" G="0.0521238" T="0.0190611"/>
      <pos A="0.893723" C="0.0250725" G="0.0461124" T="0.0350915"/>
      <pos A="0.904744" C="0.0250725" G="0.0160554" T="0.0541276"/>
      <pos A="0.104223" C="0.842626" G="0.0340896" T="0.0190611"/>
      <pos A="0.115244" C="0.812569" G="0.0390991" T="0.0330877"/>
      <pos A="0.841783" C="0.060079" G="0.0520718" T="0.0460664"/>
      <pos A="0.839781" C="0.0650835" G="0.0550745" T="0.040061"/>
      <pos A="0.124386" C="0.040141" G="0.0521758" T="0.783297"/>
      <pos A="0.164338" C="0.736424" G="0.0451105" T="0.0541276"/>
      <pos A="0.144444" C="0.0692261" G="0.0461584" T="0.740172"/>
      <pos A="0.817761" C="0.124137" G="0.0180412" T="0.040061"/>
      <pos A="0.83946" C="0.107336" G="0.00503955" T="0.0481642"/>
      <pos A="0.172353" C="0.765479" G="0.00202885" T="0.060139"/>
      <pos A="0.305605" C="0.539049" G="0.0290801" T="0.126265"/>
      <pos A="0.54661" C="0.158484" G="0.0431497" T="0.251755"/>
    </motif>
    <motif db="0" id="0004_0005_7583_0.3596_0.3261_012_127" length="116" nsites="998">
      <pos A="0.331655" C="0.292581" G="0.143298" T="0.232467"/>
      <pos A="0.252505" C="0.0942036" G="0.457895" T="0.195396"/>
      <pos A="0.233469" C="0.16033" G="0.0972093" T="0.508992"/>
      <pos A="0.678994" C="0.123383" G="0.080258" T="0.117365"/>
      <pos A="0.715384" C="0.0761694" G="0.070158" T="0.138288"/>
      <pos A="0.540512" C="0.180187" G="0.0670853" T="0.212216"/>
      <pos A="0.480457" C="0.221224" G="0.0981132" T="0.200205"/>
      <pos A="0.107121" C="0.0710889" G="0.0740916" T="0.747698"/>
      <pos A="0.0591371" C="0.769487" G="0.0511219" T="0.120253"/>
      <pos A="0.107228" C="0.800546" G="0.0491181" T="0.0431067"/>
      <pos A="0.0922928" C="0.785302" G="0.0391381" T="0.0832667"/>
      <pos A="0.656272" C="0.0481162" G="0.263526" T="0.0320858"/>
      <pos A="0.825418" C="0.0250975" G="0.0230917" T="0.126391"/>
      <pos A="0.118249" C="0.0230687" G="0.0541276" T="0.804553"/>
      <pos A="0.0561314" C="0.0591371" G="0.0481162" T="0.836614"/>
      <pos A="0.0230457" C="0.0160394" G="0.0160394" T="0.944875"/>
      <pos A="0.193587" C="0.0140656" G="0.0170743" T="0.775273"/>
      <pos A="0.0411029" C="0.135282" G="0.0150535" T="0.808561"/>
      <pos A="0.010034" C="0.010034" G="0.942874" T="0.0370583"/>
      <pos A="0.0170573" C="0.00904214" G="0.962855" T="0.0110459"/>
      <pos A="0.97087" C="0.00503455" G="0.0130497" T="0.0110459"/>
      <pos A="0.979887" C="0.00503455" G="0.00904214" T="0.00603645"/>
      <pos A="0.926859" C="2.50476e-05" G="0.0560754" T="0.0170403"/>
      <pos A="0.983894" C="0.00202885" G="0.00703834" T="0.00703834"/>
      <pos A="0.643893" C="0.00203085" G="0.00303375" T="0.351043"/>
      <pos A="0.00904214" C="0.975879" G="0.00703834" T="0.00804024"/>
      <pos A="0.00904214" C="0.00102695" G="0.937807" T="0.0521238"/>
      <pos A="0.0531257" C="0.00202885" G="0.00703834" T="0.937807"/>
      <pos A="0.0220668" C="0.00202885" G="0.969868" T="0.00603645"/>
      <pos A="0.9869" C="0.00102695" G="0.00904214" T="0.00303075"/>
      <pos A="0.988904" C="2.50476e-05" G="0.00503455" T="0.00603645"/>
      <pos A="0.00904214" C="2.50476e-05" G="0.00703834" T="0.983894"/>
      <pos A="0.985898" C="2.50476e-05" G="0.00703834" T="0.00703834"/>
      <pos A="0.010044" C="0.00403265" G="0.982893" T="0.00303075"/>
      <pos A="0.00804024" C="0.00202885" G="0.982893" T="0.00703834"/>
      <pos A="0.00904214" C="0.00403265" G="0.00703834" T="0.979887"/>
      <pos A="0.983878" C="0.00102795" G="0.00905114" T="0.00604244"/>
      <pos A="0.0110459" C="2.50476e-05" G="0.984896" T="0.00403265"/>
      <pos A="0.984896" C="2.50476e-05" G="0.00703834" T="0.00804024"/>
      <pos A="0.00903314" C="2.50476e-05" G="0.00402865" T="0.986913"/>
      <pos A="0.00303375" C="2.50476e-05" G="0.00804824" T="0.988893"/>
      <pos A="0.00302775" C="0.00102595" G="0.986913" T="0.00903314"/>
      <pos A="0.00703834" C="2.50476e-05" G="0.988904" T="0.00403265"/>
      <pos A="0.985898" C="2.50476e-05" G="0.00804024" T="0.00603645"/>
      <pos A="0.99191" C="2.50476e-05" G="0.00303075" T="0.00503455"/>
      <pos A="0.99191" C="2.50476e-05" G="0.00403265" T="0.00403265"/>
      <pos A="0.99191" C="0.00102695" G="0.00503455" T="0.00202885"/>
      <pos A="0.986913" C="0.00202685" G="0.00402865" T="0.00703135"/>
      <pos A="0.0140376" C="2.50476e-05" G="0.00202685" T="0.98391"/>
      <pos A="0.00904214" C="0.00202885" G="0.00703834" T="0.981891"/>
      <pos A="0.00303075" C="0.00202885" G="0.980889" T="0.0140516"/>
      <pos A="0.00604244" C="0.00102795" G="0.976858" T="0.0160714"/>
      <pos A="0.0561314" C="0.00102695" G="0.0160554" T="0.926786"/>
      <pos A="0.97087" C="0.00303075" G="0.00703834" T="0.0190611"/>
      <pos A="0.0511219" C="0.00202885" G="0.00603645" T="0.940813"/>
      <pos A="0.0250725" C="0.00403265" G="0.96586" T="0.00503455"/>
      <pos A="0.929792" C="0.00603645" G="0.00603645" T="0.0581352"/>
      <pos A="0.0180592" C="0.963856" G="0.0110459" T="0.00703834"/>
      <pos A="0.972874" C="0.00303075" G="0.00703834" T="0.0170573"/>
      <pos A="0.972874" C="0.00904214" G="0.00703834" T="0.0110459"/>
      <pos A="0.0220668" C="0.00303075" G="0.00603645" T="0.968866"/>
      <pos A="0.968866" C="0.00503455" G="0.00703834" T="0.0190611"/>
      <pos A="0.0180592" C="0.0421048" G="0.913761" T="0.0260744"/>
      <pos A="0.0210649" C="0.956843" G="0.0110459" T="0.0110459"/>
      <pos A="0.969868" C="0.00603645" G="0.0180592" T="0.00603645"/>
      <pos A="0.972874" C="0.0130497" G="0.00804024" T="0.00603645"/>
      <pos A="0.0290511" C="0.956886" G="0.00803225" T="0.00603045"/>
      <pos A="0.0260484" C="0.00903314" G="0.00402865" T="0.96089"/>
      <pos A="0.967864" C="0.0180592" G="0.00603645" T="0.00804024"/>
      <pos A="0.020063" C="0.00403265" G="0.956843" T="0.0190611"/>
      <pos A="0.979867" C="0.00503955" G="0.00503955" T="0.010054"/>
      <pos A="0.0220668" C="0.00703834" G="0.0170573" T="0.953837"/>
      <pos A="0.0311149" C="0.00804824" G="0.00704534" T="0.953791"/>
      <pos A="0.0180592" C="0.0110459" G="0.947826" T="0.0230687"/>
      <pos A="0.0230457" C="0.010034" G="0.944875" T="0.0220448"/>
      <pos A="0.952836" C="0.00603645" G="0.0230687" T="0.0180592"/>
      <pos A="0.0551845" C="0.00503955" G="0.0271033" T="0.912672"/>
      <pos A="0.956843" C="0.00202885" G="0.0180592" T="0.0230687"/>
      <pos A="0.0320858" C="0.00202885" G="0.935803" T="0.030082"/>
      <pos A="0.958847" C="0.00303075" G="0.0180592" T="0.020063"/>
      <pos A="0.0321178" C="0.00203085" G="0.030112" T="0.935738"/>
      <pos A="0.941815" C="0.00202885" G="0.0190611" T="0.0370953"/>
      <pos A="0.0310839" C="0.00804024" G="0.0260744" T="0.934801"/>
      <pos A="0.0451555" C="0.902643" G="0.0261004" T="0.0261004"/>
      <pos A="0.931864" C="0.0120358" G="0.0250475" T="0.0310529"/>
      <pos A="0.0411439" C="0.020083" G="0.914677" T="0.0240946"/>
      <pos A="0.0540736" C="0.0110349" G="0.0210439" T="0.913847"/>
      <pos A="0.925858" C="0.0130367" G="0.0320538" T="0.0290511"/>
      <pos A="0.933799" C="0.0110459" G="0.0170573" T="0.0380972"/>
      <pos A="0.0621428" C="0.0140516" G="0.0280782" T="0.895727"/>
      <pos A="0.0662174" C="0.0180772" G="0.886596" T="0.0291091"/>
      <pos A="0.0421468" C="0.0130627" G="0.893617" T="0.0511729"/>
      <pos A="0.0561314" C="0.0190611" G="0.900737" T="0.0240706"/>
      <pos A="0.903646" C="0.0130627" G="0.0491671" T="0.0341236"/>
      <pos A="0.90775" C="0.0310839" G="0.0461124" T="0.0150535"/>
      <pos A="0.906748" C="0.0370953" G="0.0270763" T="0.0290801"/>
      <pos A="0.0871903" C="0.858656" G="0.0320858" T="0.0220668"/>
      <pos A="0.10533" C="0.842469" G="0.0261004" T="0.0261004"/>
      <pos A="0.888714" C="0.0591371" G="0.0260744" T="0.0260744"/>
      <pos A="0.878816" C="0.0540736" G="0.0260484" T="0.0410619"/>
      <pos A="0.0993131" C="0.0672203" G="0.0291091" T="0.804357"/>
      <pos A="0.103221" C="0.788523" G="0.0411029" T="0.0671523"/>
      <pos A="0.116362" C="0.0632087" G="0.0732377" T="0.747192"/>
      <pos A="0.832775" C="0.0861024" G="0.0270493" T="0.0540736"/>
      <pos A="0.848637" C="0.0821808" G="0.00703834" T="0.0621428"/>
      <pos A="0.157324" C="0.777502" G="0.0170573" T="0.0481162"/>
      <pos A="0.304604" C="0.508992" G="0.0831827" T="0.103221"/>
      <pos A="0.556526" C="0.116129" G="0.0610799" T="0.266264"/>
      <pos A="0.742436" C="0.109232" G="0.030082" T="0.118249"/>
      <pos A="0.159328" C="0.154319" G="0.0511219" T="0.635232"/>
      <pos A="0.164173" C="0.652613" G="0.0961114" T="0.0871033"/>
      <pos A="0.147157" C="0.137148" G="0.253253" T="0.462441"/>
      <pos A="0.679316" C="0.142296" G="0.0511219" T="0.127267"/>
      <pos A="0.680638" C="0.147157" G="0.05007" T="0.122135"/>
      <pos A="0.222448" C="0.611186" G="0.0781732" T="0.0881922"/>
      <pos A="0.555079" C="0.148307" G="0.0972093" T="0.199404"/>
    </motif>
    <motif db="0" id="0004_0010_4819_0.3574_0.3413_008_127" length="120" nsites="998">
      <pos A="0.250752" C="0.147452" G="0.455345" T="0.146449"/>
      <pos A="0.0942036" C="0.291579" G="0.39177" T="0.222448"/>
      <pos A="0.421827" C="0.179366" G="0.293583" T="0.105225"/>
      <pos A="0.636598" C="0.0370583" G="0.0560754" T="0.270268"/>
      <pos A="0.66028" C="0.219442" G="0.0280782" T="0.0921998"/>
      <pos A="0.0821808" C="0.0140516" G="0.746443" T="0.157324"/>
      <pos A="0.0350915" C="0.040101" G="0.0280782" T="0.896729"/>
      <pos A="0.936741" C="0.0230917" G="0.0190801" T="0.0210859"/>
      <pos A="0.885593" C="0.0180772" G="0.0180772" T="0.0782522"/>
      <pos A="0.895727" C="0.0230687" G="0.00904214" T="0.0721618"/>
      <pos A="0.829772" C="0.0921078" G="0.0440646" T="0.0340556"/>
      <pos A="0.010044" C="2.50476e-05" G="0.00703834" T="0.982893"/>
      <pos A="0.0190611" C="0.269537" G="0.00503455" T="0.706367"/>
      <pos A="0.0180592" C="0.966862" G="0.00303075" T="0.0120478"/>
      <pos A="0.0230687" C="0.957845" G="0.00102695" T="0.0180592"/>
      <pos A="0.943761" C="0.00102795" G="0.0391381" T="0.0160714"/>
      <pos A="0.97087" C="0.00202885" G="0.00202885" T="0.0250725"/>
      <pos A="0.0370953" C="0.00303075" G="0.00904214" T="0.950832"/>
      <pos A="0.0180592" C="0.00904214" G="0.00303075" T="0.969868"/>
      <pos A="0.0160554" C="0.00303075" G="0.00403265" T="0.976881"/>
      <pos A="0.121134" C="0.00202685" G="0.00202685" T="0.874812"/>
      <pos A="0.00803225" C="0.020043" G="0.00402865" T="0.967896"/>
      <pos A="0.00403265" C="0.00303075" G="0.980889" T="0.0120478"/>
      <pos A="0.00703834" C="0.00303075" G="0.981891" T="0.00804024"/>
      <pos A="0.986887" C="0.00503955" G="0.00102795" T="0.00704534"/>
      <pos A="0.985884" C="2.50476e-05" G="0.00403665" T="0.010054"/>
      <pos A="0.9719" C="2.50476e-05" G="0.0170403" T="0.0110349"/>
      <pos A="0.967864" C="0.00202885" G="0.0120478" T="0.0180592"/>
      <pos A="0.633229" C="0.00804024" G="0.00102695" T="0.357704"/>
      <pos A="0.010044" C="0.963856" G="0.00804024" T="0.0180592"/>
      <pos A="0.0170573" C="0.00102695" G="0.811567" T="0.170349"/>
      <pos A="0.0220668" C="0.00202885" G="0.0160554" T="0.959849"/>
      <pos A="0.030112" C="0.00102795" G="0.964823" T="0.00403665"/>
      <pos A="0.976881" C="0.00102695" G="0.0120478" T="0.010044"/>
      <pos A="0.973875" C="0.00102695" G="0.00403265" T="0.0210649"/>
      <pos A="0.0180592" C="2.50476e-05" G="0.0130497" T="0.968866"/>
      <pos A="0.973875" C="0.00303075" G="0.0190611" T="0.00403265"/>
      <pos A="0.020063" C="0.00603645" G="0.967864" T="0.00603645"/>
      <pos A="0.0170573" C="0.00102695" G="0.958847" T="0.0230687"/>
      <pos A="0.0270493" C="0.00202685" G="0.0110349" T="0.959889"/>
      <pos A="0.978885" C="0.00102695" G="0.0120478" T="0.00804024"/>
      <pos A="0.0240706" C="2.50476e-05" G="0.961853" T="0.0140516"/>
      <pos A="0.968897" C="2.50476e-05" G="0.0110349" T="0.020043"/>
      <pos A="0.0160554" C="0.00102695" G="0.0120478" T="0.97087"/>
      <pos A="0.0150385" C="2.50476e-05" G="0.0180412" T="0.966895"/>
      <pos A="0.0160554" C="0.00102695" G="0.967864" T="0.0150535"/>
      <pos A="0.020063" C="0.00102695" G="0.97087" T="0.00804024"/>
      <pos A="0.959809" C="2.50476e-05" G="0.0321178" T="0.00804824"/>
      <pos A="0.968866" C="0.00102695" G="0.0110459" T="0.0190611"/>
      <pos A="0.98087" C="0.00102795" G="0.00704534" T="0.0110569"/>
      <pos A="0.962855" C="0.00303075" G="0.0170573" T="0.0170573"/>
      <pos A="0.966862" C="0.00102695" G="0.0110459" T="0.0210649"/>
      <pos A="0.020043" C="0.00402865" G="0.0160394" T="0.959889"/>
      <pos A="0.0190611" C="0.00403265" G="0.0190611" T="0.957845"/>
      <pos A="0.0180772" C="0.00403665" G="0.950783" T="0.0271033"/>
      <pos A="0.0220448" C="0.00102595" G="0.951882" T="0.0250475"/>
      <pos A="0.0531257" C="0.00503455" G="0.0240706" T="0.917769"/>
      <pos A="0.938809" C="0.00403265" G="0.0230687" T="0.0340896"/>
      <pos A="0.0470673" C="0.00703135" G="0.020043" T="0.925858"/>
      <pos A="0.0421048" C="0.010044" G="0.927788" T="0.020063"/>
      <pos A="0.929721" C="0.0110569" G="0.0170743" T="0.0421468"/>
      <pos A="0.0421468" C="0.929721" G="0.0170743" T="0.0110569"/>
      <pos A="0.93887" C="0.0150385" G="0.0150385" T="0.0310529"/>
      <pos A="0.952836" C="0.0140516" G="0.00904214" T="0.0240706"/>
      <pos A="0.0370953" C="0.00503455" G="0.0220668" T="0.935803"/>
      <pos A="0.943818" C="0.0110459" G="0.0220668" T="0.0230687"/>
      <pos A="0.0360934" C="0.0340896" G="0.899735" T="0.030082"/>
      <pos A="0.0360574" C="0.925858" G="0.0160394" T="0.0220448"/>
      <pos A="0.952836" C="0.0140516" G="0.0190611" T="0.0140516"/>
      <pos A="0.952836" C="0.010044" G="0.0180592" T="0.0190611"/>
      <pos A="0.0431067" C="0.930794" G="0.0120478" T="0.0140516"/>
      <pos A="0.0330877" C="0.0130497" G="0.0160554" T="0.937807"/>
      <pos A="0.957845" C="0.0150535" G="0.0150535" T="0.0120478"/>
      <pos A="0.0290801" C="0.00703834" G="0.940813" T="0.0230687"/>
      <pos A="0.967832" C="0.00704534" G="0.0110569" T="0.0140656"/>
      <pos A="0.0280782" C="0.00403265" G="0.0150535" T="0.952836"/>
      <pos A="0.0260744" C="0.0130497" G="0.0140516" T="0.946824"/>
      <pos A="0.0210649" C="0.0140516" G="0.946824" T="0.0180592"/>
      <pos A="0.0291091" C="0.00303375" G="0.950783" T="0.0170743"/>
      <pos A="0.955797" C="0.00403665" G="0.0180772" T="0.0220888"/>
      <pos A="0.0810979" C="0.0110349" G="0.0160394" T="0.891828"/>
      <pos A="0.962855" C="0.00403265" G="0.0130497" T="0.020063"/>
      <pos A="0.0240946" C="0.00203085" G="0.943761" T="0.030112"/>
      <pos A="0.954884" C="0.00402865" G="0.0210439" T="0.020043"/>
      <pos A="0.0240706" C="0.00102695" G="0.0220668" T="0.952836"/>
      <pos A="0.969868" C="2.50476e-05" G="0.0140516" T="0.0160554"/>
      <pos A="0.0140376" C="0.00202685" G="0.0140376" T="0.969898"/>
      <pos A="0.020043" C="0.947878" G="0.0160394" T="0.0160394"/>
      <pos A="0.975903" C="2.50476e-05" G="0.0190421" T="0.00502955"/>
      <pos A="0.0180592" C="0.00503455" G="0.971872" T="0.00503455"/>
      <pos A="0.0180592" C="0.00603645" G="0.00603645" T="0.969868"/>
      <pos A="0.976881" C="0.00102695" G="0.010044" T="0.0120478"/>
      <pos A="0.981891" C="0.00503455" G="0.00904214" T="0.00403265"/>
      <pos A="0.0180412" C="0.00603045" G="0.00703135" T="0.968897"/>
      <pos A="0.0140516" C="0.0120478" G="0.96586" T="0.00804024"/>
      <pos A="0.0150685" C="0.00403665" G="0.971844" T="0.00905114"/>
      <pos A="0.010034" C="0.010034" G="0.974902" T="0.00502955"/>
      <pos A="0.97087" C="0.00703834" G="0.00403265" T="0.0180592"/>
      <pos A="0.982893" C="0.00603645" G="0.00603645" T="0.00503455"/>
      <pos A="0.971872" C="0.00703834" G="0.00804024" T="0.0130497"/>
      <pos A="0.0160714" C="0.950783" G="0.0150685" T="0.0180772"/>
      <pos A="0.030112" C="0.946771" G="0.00604244" T="0.0170743"/>
      <pos A="0.953837" C="0.0150535" G="0.0120478" T="0.0190611"/>
      <pos A="0.956843" C="0.00904214" G="0.0110459" T="0.0230687"/>
      <pos A="0.0631447" C="0.0370953" G="0.0230687" T="0.876691"/>
      <pos A="0.0510709" C="0.878816" G="0.0380592" T="0.0320538"/>
      <pos A="0.0962074" C="0.0551295" G="0.0861884" T="0.762474"/>
      <pos A="0.865804" C="0.0520718" G="0.0340556" T="0.0480682"/>
      <pos A="0.887712" C="0.0591371" G="0.00503455" T="0.0481162"/>
      <pos A="0.119371" C="0.826421" G="0.0120598" T="0.0421468"/>
      <pos A="0.280558" C="0.532036" G="0.0982112" T="0.0891941"/>
      <pos A="0.55007" C="0.090196" G="0.0671523" T="0.292581"/>
      <pos A="0.780728" C="0.090106" G="0.0240466" T="0.10512"/>
      <pos A="0.135282" C="0.133279" G="0.0380972" T="0.693343"/>
      <pos A="0.142438" C="0.709081" G="0.0682232" T="0.080258"/>
      <pos A="0.142296" C="0.120253" G="0.232467" T="0.504984"/>
      <pos A="0.721116" C="0.121377" G="0.0431497" T="0.114357"/>
      <pos A="0.709373" C="0.127267" G="0.0481162" T="0.115244"/>
      <pos A="0.189385" C="0.648257" G="0.0631447" T="0.0992131"/>
      <pos A="0.535041" C="0.158326" G="0.0952055" T="0.211427"/>
    </motif>
    <motif db="0" id="0004_0011_3437_0.3615_0.3283_014_128" length="115" nsites="998">
      <pos A="0.657617" C="0.147157" G="0.102117" T="0.0931087"/>
      <pos A="0.309924" C="0.151464" G="0.184561" T="0.354052"/>
      <pos A="0.462905" C="0.0471143" G="0.0481162" T="0.441865"/>
      <pos A="0.625213" C="0.0551295" G="0.040101" T="0.279556"/>
      <pos A="0.241484" C="0.0651485" G="0.0441086" T="0.649259"/>
      <pos A="0.140292" C="0.0370953" G="0.0320858" T="0.790527"/>
      <pos A="0.0962074" C="0.164338" G="0.0230687" T="0.716386"/>
      <pos A="0.0952055" C="0.765479" G="0.0210649" T="0.118249"/>
      <pos A="0.131275" C="0.753457" G="0.0110459" T="0.104223"/>
      <pos A="0.793533" C="0.0641466" G="0.0411029" T="0.101217"/>
      <pos A="0.819582" C="0.0431067" G="0.00503455" T="0.132277"/>
      <pos A="0.138288" C="0.0380972" G="0.0190611" T="0.804553"/>
      <pos A="0.0841006" C="0.0260484" G="0.0130367" T="0.876814"/>
      <pos A="0.0612029" C="0.00604244" G="0.0160714" T="0.916683"/>
      <pos A="0.102219" C="0.0180592" G="0.020063" T="0.859658"/>
      <pos A="0.0591371" C="0.0471143" G="0.0581352" T="0.835612"/>
      <pos A="0.0471143" C="0.020063" G="0.81858" T="0.114242"/>
      <pos A="0.0871903" C="0.020063" G="0.816576" T="0.0761694"/>
      <pos A="0.87055" C="0.010054" G="0.0612029" T="0.0581942"/>
      <pos A="0.909754" C="0.00503455" G="0.0340896" T="0.0511219"/>
      <pos A="0.900737" C="0.00403265" G="0.0461124" T="0.0491181"/>
      <pos A="0.91276" C="0.00804024" G="0.0290801" T="0.05012"/>
      <pos A="0.665289" C="0.0280782" G="0.0190611" T="0.287571"/>
      <pos A="0.0751675" C="0.82359" G="0.05012" T="0.0511219"/>
      <pos A="0.0551845" C="0.0261004" G="0.809372" T="0.109342"/>
      <pos A="0.080097" C="0.0110349" G="0.0710889" T="0.837779"/>
      <pos A="0.0911979" C="0.010044" G="0.865669" T="0.0330877"/>
      <pos A="0.927788" C="0.00804024" G="0.0411029" T="0.0230687"/>
      <pos A="0.946824" C="0.00102695" G="0.020063" T="0.0320858"/>
      <pos A="0.0790961" C="2.50476e-05" G="0.0180412" T="0.902838"/>
      <pos A="0.933865" C="0.00603045" G="0.0330547" T="0.0270493"/>
      <pos A="0.0411029" C="0.00303075" G="0.937807" T="0.0180592"/>
      <pos A="0.0270763" C="0.00503455" G="0.940813" T="0.0270763"/>
      <pos A="0.0330877" C="2.50476e-05" G="0.0340896" T="0.932798"/>
      <pos A="0.945768" C="0.00503955" G="0.0281062" T="0.0210859"/>
      <pos A="0.0411029" C="2.50476e-05" G="0.940813" T="0.0180592"/>
      <pos A="0.956886" C="2.50476e-05" G="0.0150385" T="0.0280502"/>
      <pos A="0.0210859" C="2.50476e-05" G="0.020083" T="0.958806"/>
      <pos A="0.0120358" C="0.00102595" G="0.0290511" T="0.957887"/>
      <pos A="0.0150385" C="2.50476e-05" G="0.963892" T="0.0210439"/>
      <pos A="0.0250725" C="2.50476e-05" G="0.968866" T="0.00603645"/>
      <pos A="0.974877" C="2.50476e-05" G="0.020063" T="0.00503455"/>
      <pos A="0.9869" C="0.00102695" G="0.00603645" T="0.00603645"/>
      <pos A="0.987902" C="2.50476e-05" G="0.00603645" T="0.00603645"/>
      <pos A="0.977883" C="2.50476e-05" G="0.00804024" T="0.0140516"/>
      <pos A="0.973875" C="0.00303075" G="0.00703834" T="0.0160554"/>
      <pos A="0.0160554" C="0.00102695" G="0.00804024" T="0.974877"/>
      <pos A="0.0110459" C="0.00202885" G="0.0160554" T="0.97087"/>
      <pos A="0.010034" C="2.50476e-05" G="0.9719" T="0.0180412"/>
      <pos A="0.0150535" C="0.00202885" G="0.96586" T="0.0170573"/>
      <pos A="0.0391381" C="0.00303375" G="0.0150685" T="0.942759"/>
      <pos A="0.96089" C="0.00603045" G="0.00703135" T="0.0260484"/>
      <pos A="0.0280502" C="0.00402865" G="0.00903314" T="0.958888"/>
      <pos A="0.020083" C="0.00604244" G="0.964823" T="0.00905114"/>
      <pos A="0.958888" C="0.00502955" G="0.00502955" T="0.0310529"/>
      <pos A="0.0230457" C="0.961891" G="0.00603045" T="0.00903314"/>
      <pos A="0.97087" C="0.00403265" G="0.0120478" T="0.0130497"/>
      <pos A="0.969898" C="0.00302775" G="0.010034" T="0.0170403"/>
      <pos A="0.0170573" C="0.00804024" G="0.00703834" T="0.967864"/>
      <pos A="0.968866" C="0.00804024" G="0.010044" T="0.0130497"/>
      <pos A="0.0230917" C="0.0240946" G="0.935738" T="0.0170743"/>
      <pos A="0.0170573" C="0.957845" G="0.0110459" T="0.0140516"/>
      <pos A="0.969898" C="0.00603045" G="0.0120358" T="0.0120358"/>
      <pos A="0.97087" C="0.00403265" G="0.00703834" T="0.0180592"/>
      <pos A="0.0180592" C="0.961853" G="0.0130497" T="0.00703834"/>
      <pos A="0.0220888" C="0.00403665" G="0.010054" T="0.96382"/>
      <pos A="0.976881" C="0.00703834" G="0.00703834" T="0.00904214"/>
      <pos A="0.0190801" C="0.00102795" G="0.962818" T="0.0170743"/>
      <pos A="0.975879" C="0.00403265" G="0.0110459" T="0.00904214"/>
      <pos A="0.0120598" C="0.00403665" G="0.00905114" T="0.974852"/>
      <pos A="0.0210439" C="0.00302775" G="0.00703135" T="0.968897"/>
      <pos A="0.0110349" C="0.00803225" G="0.9719" T="0.00903314"/>
      <pos A="0.0150535" C="0.00804024" G="0.967864" T="0.00904214"/>
      <pos A="0.981873" C="0.00203085" G="0.00704534" T="0.00905114"/>
      <pos A="0.0731637" C="0.00503455" G="0.00804024" T="0.913761"/>
      <pos A="0.978885" C="2.50476e-05" G="0.00904214" T="0.0120478"/>
      <pos A="0.0120478" C="0.00102695" G="0.971872" T="0.0150535"/>
      <pos A="0.976858" C="2.50476e-05" G="0.0110569" T="0.0120598"/>
      <pos A="0.0130497" C="0.00403265" G="0.010044" T="0.972874"/>
      <pos A="0.979887" C="0.00102695" G="0.00904214" T="0.010044"/>
      <pos A="0.0120478" C="0.00102695" G="0.0120478" T="0.974877"/>
      <pos A="0.0130497" C="0.956843" G="0.0210649" T="0.00904214"/>
      <pos A="0.981891" C="0.00102695" G="0.010044" T="0.00703834"/>
      <pos A="0.0210649" C="0.00403265" G="0.96586" T="0.00904214"/>
      <pos A="0.0140376" C="0.00803225" G="0.00202685" T="0.975903"/>
      <pos A="0.985898" C="0.00403265" G="0.00503455" T="0.00503455"/>
      <pos A="0.982893" C="0.00403265" G="0.00403265" T="0.00904214"/>
      <pos A="0.0140516" C="0.00603645" G="0.00804024" T="0.971872"/>
      <pos A="0.0150535" C="0.00603645" G="0.972874" T="0.00603645"/>
      <pos A="0.00804024" C="0.00603645" G="0.975879" T="0.010044"/>
      <pos A="0.00804824" C="0.00704534" G="0.979867" T="0.00503955"/>
      <pos A="0.978906" C="0.00803225" G="0.00102595" T="0.0120358"/>
      <pos A="0.975879" C="0.00804024" G="0.00804024" T="0.00804024"/>
      <pos A="0.971872" C="0.00703834" G="0.0120478" T="0.00904214"/>
      <pos A="0.0220668" C="0.94482" G="0.0150535" T="0.0180592"/>
      <pos A="0.0240706" C="0.956843" G="0.00904214" T="0.010044"/>
      <pos A="0.953883" C="0.020043" G="0.00703135" T="0.0190421"/>
      <pos A="0.965826" C="0.0150685" G="0.00704534" T="0.0120598"/>
      <pos A="0.0531787" C="0.0321178" G="0.0120598" T="0.902643"/>
      <pos A="0.0370953" C="0.915765" G="0.0190611" T="0.0280782"/>
      <pos A="0.0631447" C="0.0491181" G="0.0962074" T="0.791529"/>
      <pos A="0.902838" C="0.0270493" G="0.020043" T="0.05007"/>
      <pos A="0.924782" C="0.0411029" G="0.00403265" T="0.030082"/>
      <pos A="0.0721618" C="0.879697" G="0.0150535" T="0.0330877"/>
      <pos A="0.245491" C="0.577121" G="0.121255" T="0.0561314"/>
      <pos A="0.585136" C="0.0651485" G="0.0581352" T="0.291579"/>
      <pos A="0.852645" C="0.0661504" G="0.020063" T="0.0611409"/>
      <pos A="0.0981132" C="0.0881042" G="0.0370583" T="0.776724"/>
      <pos A="0.0952055" C="0.794534" G="0.0551295" T="0.0551295"/>
      <pos A="0.108339" C="0.0752435" G="0.323965" T="0.492453"/>
      <pos A="0.80255" C="0.0921998" G="0.030082" T="0.0751675"/>
      <pos A="0.775498" C="0.0952055" G="0.0330877" T="0.0962074"/>
      <pos A="0.140292" C="0.729411" G="0.0481162" T="0.0821808"/>
      <pos A="0.590146" C="0.134281" G="0.0861884" T="0.189385"/>
      <pos A="0.165339" C="0.225453" G="0.214433" T="0.394775"/>
    </motif>
    <motif db="0" id="0010_0003_1159_0.3277_0.2612_024_130" length="107" nsites="998">
      <pos A="0.250752" C="0.536581" G="0.0541816" T="0.158484"/>
      <pos A="0.157324" C="0.546062" G="0.0661504" T="0.230463"/>
      <pos A="0.574542" C="0.0740916" G="0.123136" T="0.22823"/>
      <pos A="0.671301" C="0.0360934" G="0.0581352" T="0.234471"/>
      <pos A="0.212429" C="0.0531257" G="0.0481162" T="0.686329"/>
      <pos A="0.0992131" C="0.0741656" G="0.0671523" T="0.759468"/>
      <pos A="0.121255" C="0.0441086" G="0.142296" T="0.692341"/>
      <pos A="0.145156" C="0.0480682" G="0.143154" T="0.663623"/>
      <pos A="0.217656" C="0.0973073" G="0.0431497" T="0.641887"/>
      <pos A="0.175358" C="0.0340896" G="0.659278" T="0.131275"/>
      <pos A="0.175358" C="0.0230687" G="0.712379" T="0.0891941"/>
      <pos A="0.813571" C="0.0150535" G="0.0972093" T="0.0741656"/>
      <pos A="0.826769" C="0.010034" G="0.0520718" T="0.111125"/>
      <pos A="0.771491" C="0.0651485" G="0.0982112" T="0.0651485"/>
      <pos A="0.831436" C="0.00704534" G="0.0932957" T="0.0682232"/>
      <pos A="0.647255" C="0.00904214" G="0.0491181" T="0.294585"/>
      <pos A="0.102219" C="0.729411" G="0.118249" T="0.05012"/>
      <pos A="0.147305" C="0.020063" G="0.777502" T="0.0551295"/>
      <pos A="0.165504" C="0.00604244" G="0.0722348" T="0.756218"/>
      <pos A="0.113354" C="0.0110569" G="0.782294" T="0.0932957"/>
      <pos A="0.898733" C="0.00804024" G="0.0421048" T="0.0511219"/>
      <pos A="0.891611" C="0.00704534" G="0.0551845" T="0.0461584"/>
      <pos A="0.0511729" C="0.00704534" G="0.0602" T="0.881582"/>
      <pos A="0.893829" C="0.00603045" G="0.040061" T="0.060079"/>
      <pos A="0.0421048" C="0.010044" G="0.922779" T="0.0250725"/>
      <pos A="0.0260744" C="0.00202885" G="0.942817" T="0.0290801"/>
      <pos A="0.0551295" C="2.50476e-05" G="0.0250725" T="0.919773"/>
      <pos A="0.965894" C="2.50476e-05" G="0.0190421" T="0.0150385"/>
      <pos A="0.0561314" C="2.50476e-05" G="0.934801" T="0.00904214"/>
      <pos A="0.978885" C="2.50476e-05" G="0.00804024" T="0.0130497"/>
      <pos A="0.0260484" C="2.50476e-05" G="0.00502955" T="0.968897"/>
      <pos A="2.50476e-05" C="2.50476e-05" G="0.0120358" T="0.987914"/>
      <pos A="0.00502955" C="2.50476e-05" G="0.974902" T="0.020043"/>
      <pos A="0.00502955" C="2.50476e-05" G="0.99492" T="2.50476e-05"/>
      <pos A="0.975903" C="2.50476e-05" G="0.020043" T="0.00402865"/>
      <pos A="0.989916" C="2.50476e-05" G="2.50476e-05" T="0.010034"/>
      <pos A="0.995921" C="2.50476e-05" G="2.50476e-05" T="0.00402865"/>
      <pos A="0.985912" C="2.50476e-05" G="0.00402865" T="0.010034"/>
      <pos A="0.9869" C="2.50476e-05" G="0.010044" T="0.00303075"/>
      <pos A="0.0190421" C="2.50476e-05" G="2.50476e-05" T="0.980908"/>
      <pos A="2.50476e-05" C="0.010034" G="0.00302775" T="0.986913"/>
      <pos A="0.010044" C="2.50476e-05" G="0.981891" T="0.00804024"/>
      <pos A="0.010044" C="2.50476e-05" G="0.9869" T="0.00303075"/>
      <pos A="0.030052" C="2.50476e-05" G="0.00903314" T="0.96089"/>
      <pos A="0.966862" C="2.50476e-05" G="2.50476e-05" T="0.0330877"/>
      <pos A="0.00804024" C="2.50476e-05" G="0.0130497" T="0.978885"/>
      <pos A="0.00303375" C="0.010054" G="0.981873" T="0.00503955"/>
      <pos A="0.964858" C="0.00303075" G="0.00503455" T="0.0270763"/>
      <pos A="0.0160554" C="0.983894" G="2.50476e-05" T="2.50476e-05"/>
      <pos A="0.986913" C="0.00302775" G="0.010034" T="2.50476e-05"/>
      <pos A="0.9869" C="2.50476e-05" G="0.010044" T="0.00303075"/>
      <pos A="0.0150535" C="0.00503455" G="0.00102695" T="0.978885"/>
      <pos A="0.978906" C="2.50476e-05" G="0.0130367" T="0.00803225"/>
      <pos A="0.0140376" C="0.0280502" G="0.954884" T="0.00302775"/>
      <pos A="0.00102695" C="0.988904" G="0.00904214" T="0.00102695"/>
      <pos A="0.997923" C="0.00202685" G="2.50476e-05" T="2.50476e-05"/>
      <pos A="0.993919" C="2.50476e-05" G="0.00102595" T="0.00502955"/>
      <pos A="0.00302775" C="0.991918" G="2.50476e-05" T="0.00502955"/>
      <pos A="2.50476e-05" C="0.00202685" G="0.00502955" T="0.992919"/>
      <pos A="0.992912" C="2.50476e-05" G="0.00503455" T="0.00202885"/>
      <pos A="0.00502955" C="2.50476e-05" G="0.993919" T="0.00102595"/>
      <pos A="0.993919" C="0.00102595" G="2.50476e-05" T="0.00502955"/>
      <pos A="0.00603045" C="2.50476e-05" G="2.50476e-05" T="0.993919"/>
      <pos A="2.50476e-05" C="2.50476e-05" G="0.00102595" T="0.998924"/>
      <pos A="2.50476e-05" C="0.00202685" G="0.996922" T="0.00102595"/>
      <pos A="2.50476e-05" C="2.50476e-05" G="0.999925" T="2.50476e-05"/>
      <pos A="0.999925" C="2.50476e-05" G="2.50476e-05" T="2.50476e-05"/>
      <pos A="0.0420628" C="2.50476e-05" G="2.50476e-05" T="0.957887"/>
      <pos A="0.997923" C="2.50476e-05" G="0.00202685" T="2.50476e-05"/>
      <pos A="2.50476e-05" C="2.50476e-05" G="0.999925" T="2.50476e-05"/>
      <pos A="0.999925" C="2.50476e-05" G="2.50476e-05" T="2.50476e-05"/>
      <pos A="2.50476e-05" C="2.50476e-05" G="2.50476e-05" T="0.999925"/>
      <pos A="0.999925" C="2.50476e-05" G="2.50476e-05" T="2.50476e-05"/>
      <pos A="2.50476e-05" C="2.50476e-05" G="2.50476e-05" T="0.999925"/>
      <pos A="2.50476e-05" C="0.995921" G="2.50476e-05" T="0.00402865"/>
      <pos A="0.99492" C="2.50476e-05" G="0.00502955" T="2.50476e-05"/>
      <pos A="2.50476e-05" C="2.50476e-05" G="0.999925" T="2.50476e-05"/>
      <pos A="2.50476e-05" C="2.50476e-05" G="0.00403265" T="0.995917"/>
      <pos A="0.988915" C="2.50476e-05" G="0.0110349" T="2.50476e-05"/>
      <pos A="0.995921" C="0.00202685" G="0.00202685" T="2.50476e-05"/>
      <pos A="0.010034" C="2.50476e-05" G="2.50476e-05" T="0.989916"/>
      <pos A="0.00603645" C="0.0120478" G="0.977883" T="0.00403265"/>
      <pos A="0.00603645" C="0.010044" G="0.974877" T="0.00904214"/>
      <pos A="0.0350915" C="0.00102695" G="0.961853" T="0.00202885"/>
      <pos A="0.96586" C="0.0220668" G="0.00904214" T="0.00303075"/>
      <pos A="0.941756" C="0.0361294" G="0.00303375" T="0.0190801"/>
      <pos A="0.960851" C="0.0170573" G="0.0160554" T="0.00603645"/>
      <pos A="0.05007" C="0.917851" G="0.0230457" T="0.00903314"/>
      <pos A="0.0350915" C="0.902741" G="0.0310839" T="0.0310839"/>
      <pos A="0.946824" C="0.0250725" G="0.0110459" T="0.0170573"/>
      <pos A="0.925709" C="0.0331207" G="0.00704534" T="0.0341236"/>
      <pos A="0.0681542" C="0.0250725" G="0.0160554" T="0.890718"/>
      <pos A="0.0670853" C="0.899835" G="0.0110349" T="0.0220448"/>
      <pos A="0.0510709" C="0.0750925" G="0.0440646" T="0.829772"/>
      <pos A="0.904744" C="0.0671523" G="0.00102695" T="0.0270763"/>
      <pos A="0.925709" C="0.0351265" G="0.0120598" T="0.0271033"/>
      <pos A="0.060139" C="0.858656" G="0.0140516" T="0.0671523"/>
      <pos A="0.225227" C="0.578546" G="0.0841006" T="0.112126"/>
      <pos A="0.547518" C="0.0570763" G="0.0610799" T="0.334326"/>
      <pos A="0.815759" C="0.0370583" G="0.0230457" T="0.124137"/>
      <pos A="0.126265" C="0.124261" G="0.040101" T="0.709373"/>
      <pos A="0.106226" C="0.753457" G="0.0962074" T="0.0441086"/>
      <pos A="0.100115" C="0.138149" G="0.289285" T="0.47245"/>
      <pos A="0.75546" C="0.0831827" G="0.0561314" T="0.105225"/>
      <pos A="0.754458" C="0.105225" G="0.0691561" T="0.0711599"/>
      <pos A="0.119371" C="0.71209" G="0.0832667" T="0.0852725"/>
      <pos A="0.5777" C="0.108339" G="0.0862754" T="0.227685"/>
    </motif>
  </queries>
  <targets>
  </targets>
  <matches>
  </matches>
  <runtime cycles="7024910967" seconds="7024.911"/>
</tomtom>
